llm_securescan/__init__.py
llm_securescan/main.py
llm_securescan/prompts.py
llm_securescan-2025.12.21142626.dist-info/METADATA
llm_securescan-2025.12.21142626.dist-info/WHEEL
llm_securescan-2025.12.21142626.dist-info/top_level.txt
llm_securescan-2025.12.21142626.dist-info/RECORD
