Metadata-Version: 2.4
Name: llm-securescan
Version: 2025.12.21142626
Summary: A new package is designed to facilitate secure and structured user interactions with language models by analyzing and extracting specific information from user-provided text. It uses pattern matching
Author-email: llm-securescan <hi@eugene.plus>
License: MIT
Project-URL: Homepage, https://github.com/chigwell/llm-securescan
Requires-Python: >=3.9
Requires-Dist: langchain-llm7>=0.0.0
Requires-Dist: llmatch-messages>=0.0.0
Requires-Dist: langchain-core>=0.3.0
